zekeconv/__init__.py
zekeconv/io.py
zekeconv/utl.py
zekeconv/zekeconv.py
zekeconv-0.2.1.dist-info/DESCRIPTION.rst
zekeconv-0.2.1.dist-info/METADATA
zekeconv-0.2.1.dist-info/RECORD
zekeconv-0.2.1.dist-info/WHEEL
zekeconv-0.2.1.dist-info/entry_points.txt
zekeconv-0.2.1.dist-info/metadata.json
zekeconv-0.2.1.dist-info/top_level.txt
