Metadata-Version: 2.0
Name: zekeconv
Version: 0.2.1
Summary: converter between zeke dumps and directory structures
Home-page: UNKNOWN
Author: Stanislav Klenin
Author-email: stanislav.klenin@gmail.com
License: Apache Software License
Platform: UNKNOWN
